blazeverify/__init__.py
blazeverify/client.py
blazeverify/error.py
blazeverify/response.py
blazeverify-1.0.1.dist-info/LICENSE
blazeverify-1.0.1.dist-info/METADATA
blazeverify-1.0.1.dist-info/WHEEL
blazeverify-1.0.1.dist-info/top_level.txt
blazeverify-1.0.1.dist-info/RECORD
