Metadata-Version: 2.1
Name: blazeverify
Version: 1.0.1
Summary: This is the official python wrapper for the Blaze Verify API.
Home-page: https://github.com/blazeverify/blazeverify-python
Author: Blaze Verify
Author-email: support@blazeverify.com
License: MIT
Project-URL: Bug Tracker, https://github.com/blazeverify/blazeverify-python/issues
Project-URL: Documentation, https://blazeverify.com/docs/api
Project-URL: Source Code, https://github.com/blazeverify/blazeverify-python
Keywords: blazeverify email verification
Platform: UNKNOWN
Classifier: Programming Language :: Python :: 3
Classifier: License :: OSI Approved :: MIT License
Classifier: Operating System :: OS Independent
Requires-Python: >=3.6
Requires-Dist: requests
